dbrownell_ToolsDirectory/UvScaffolding_sample_file.py
dbrownell_ToolsDirectory/__init__.py
dbrownell_ToolsDirectory/py.typed
dbrownell_toolsdirectory-0.1.0.dist-info/WHEEL
dbrownell_toolsdirectory-0.1.0.dist-info/METADATA
dbrownell_toolsdirectory-0.1.0.dist-info/RECORD
