Metadata-Version: 2.3
Name: dbrownell-toolsdirectory
Version: 0.1.0
Summary: Creates functionality to manipulate the shell in support of tools defined within a tools directory.
Author: David Brownell
Author-email: David Brownell <github@DavidBrownell.com>
License: MIT
Classifier: Operating System :: MacOS
Classifier: Operating System :: Microsoft :: Windows
Classifier: Operating System :: POSIX :: Linux
Classifier: Programming Language :: Python
Classifier: Programming Language :: Python :: 3.14
Requires-Python: >=3.14
Project-URL: Documentation, https://github.com/davidbrownell/dbrownell_ToolsDirectory
Project-URL: Homepage, https://github.com/davidbrownell/dbrownell_ToolsDirectory
Project-URL: Repository, https://github.com/davidbrownell/dbrownell_ToolsDirectory
